poetry_plugin_up/__init__.py
poetry_plugin_up/command.py
poetry_plugin_up/plugin.py
poetry_plugin_up-0.9.0.dist-info/LICENSE
poetry_plugin_up-0.9.0.dist-info/METADATA
poetry_plugin_up-0.9.0.dist-info/WHEEL
poetry_plugin_up-0.9.0.dist-info/entry_points.txt
poetry_plugin_up-0.9.0.dist-info/RECORD
