Metadata-Version: 2.1
Name: poetry-plugin-up
Version: 0.9.0
Summary: Poetry plugin that updates dependencies and bumps their versions in pyproject.toml file
Home-page: https://github.com/MousaZeidBaker/poetry-plugin-up
License: MIT
Keywords: packaging,dependency,poetry,update,upgrade
Author: Mousa Zeid Baker
Requires-Python: >=3.9,<4.0
Classifier: Development Status :: 5 - Production/Stable
Classifier: License :: OSI Approved :: MIT License
Classifier: Operating System :: OS Independent
Classifier: Programming Language :: Python :: 3
Classifier: Programming Language :: Python :: 3.9
Classifier: Programming Language :: Python :: 3.10
Classifier: Programming Language :: Python :: 3.11
Requires-Dist: poetry (>=1.8.4,<3.0.0)
Project-URL: Repository, https://github.com/MousaZeidBaker/poetry-plugin-up
